{"type": "Feature", "id": 12510317, "properties": {"woe:id": 12510317, "woe:parent_id": 15000629, "woe:name": "Bou Chekif Airport", "woe:placetype": 14, "woe:placetype_name": "Airport", "woe:lang": "ENG", "iso:country": "DZ", "meta:provider": ["geoplanet:7.3.1", "geoplanet:7.3.2", "geoplanet:7.4.0", "geoplanet:7.4.1", "geoplanet:7.5.1", "geoplanet:7.5.2", "geoplanet:7.6.0", "geoplanet:7.8.1", "geoplanet:7.9.0", "geoplanet:7.10.0", "geoplanet:8.0.0", "woeplanet:8.0.0"], "meta:indexed": "2020-08-20T20:49:07.402126", "woe:alias_ENG_V": ["TID Airport", "TID"], "meta:updated": "2020-08-22T01:58:50.565134", "woe:hierarchy": {"continent": 24865670, "country": 23424740, "town": 0, "planet": 1, "county": 0, "suburb": 0, "state": 2344587, "region": 0, "localadmin": 0}, "woe:timezone_id": 28350684, "woe:hash": "sn31139kudq7", "woe:centroid": [1.4631, 35.341099], "geom:latitude": 35.341099, "geom:longitude": 1.4631, "geom:hash": "sn31139kudq7", "woe:latitude": 35.341099, "geom:centroid": [1.4631, 35.341099], "woe:longitude": 1.4631, "woe:repo": "woeplanet-airport-dz"}, "geometry": {"coordinates": [1.4631, 35.341099], "type": "Point"}}